{
  "id": "0060e3b346884a3e168df8cad23cf99675f37efe3954f854164a30b82f2f887d",
  "source": "Dnevni list Danas",
  "title": "Pobednik Evrovizije Nemo vraća trofej u znak protesta zbog Izraela",
  "subtitle": "<img alt=\"Pobednik Evrovizije Nemo vraća trofej u znak protesta zbog Izraela 30\" class=\"attachment-medium size-medium wp-post-image\" height=\"169\" src=\"https://www.danas.rs/wp-content/uploads/2025/12/63dbfa80-d703-11f0-873e-6ffe5dbb6e3d-300x169.jpg\" style=\"float: left; margin: 0 10px 10px 0;\" title=\"Pobednik Evrovizije Nemo vraća trofej u znak protesta zbog Izraela 33\" width=\"300\" /><div>Jasan je sukob između idela i vrednosti Evrovizije i onoga što je uradio Izrael, stav je švajcarskog pevača.</div>",
  "url": "https://www.danas.rs/bbc-news-serbian/pobednik-evrovizije-nemo-vraca-trofej-u-znak-protesta-zbog-izraela/",
  "published": "Fri, 12 Dec 2025 06:40:08 +0000",
  "fetched_at": "2025-12-12T08:59:55.683348",
  "full_text": "<img alt=\"Pobednik Evrovizije Nemo vraća trofej u znak protesta zbog Izraela 30\" class=\"attachment-medium size-medium wp-post-image\" height=\"169\" src=\"https://www.danas.rs/wp-content/uploads/2025/12/63dbfa80-d703-11f0-873e-6ffe5dbb6e3d-300x169.jpg\" style=\"float: left; margin: 0 10px 10px 0;\" title=\"Pobednik Evrovizije Nemo vraća trofej u znak protesta zbog Izraela 33\" width=\"300\" /><div>Jasan je sukob između idela i vrednosti Evrovizije i onoga što je uradio Izrael, stav je švajcarskog pevača.</div>"
}