{
  "id": "00ab980de7664a25547c10d0137a7d494f5c89a61aa1f4b0d85c119d402f994c",
  "source": "BBC News",
  "title": "Government data stolen in hack, minister confirms",
  "subtitle": "The trade minister says information was accessed and an investigation has been launched.",
  "url": "https://www.bbc.com/news/articles/cj4qpwprw9vo?at_medium=RSS&at_campaign=rss",
  "published": "Fri, 19 Dec 2025 08:24:18 GMT",
  "fetched_at": "2025-12-19T08:34:10.812622",
  "full_text": "The trade minister says information was accessed and an investigation has been launched."
}