{
  "id": "0676f2f1db02b71de19bd2adca6d25be54ebb7e88b6342f600c4e073221044e6",
  "source": "Dnevni list Danas",
  "title": "Macut: Zelena transformacija jedna od strateških politika Vlade",
  "subtitle": "<img alt=\"Macut: Zelena transformacija jedna od strateških politika Vlade 26\" class=\"attachment-medium size-medium wp-post-image\" height=\"169\" src=\"https://www.danas.rs/wp-content/uploads/2025/10/DJuro-Macut-RTS-printscreen-300x169.png\" style=\"float: left; margin: 0 10px 10px 0;\" title=\"Macut: Zelena transformacija jedna od strateških politika Vlade 49\" width=\"300\" />Predsednik Vlade Srbije Đuro Macut poručio je danas, na završnom događaju nacionalne ekološke kampanje za mlade \"Priroda nema alternativu. Zato deluj i ti!\", da je zelena transformacija jedna od strateških politika Vlade i da na tom putu nema važnijeg partnera od mladih.",
  "url": "https://www.danas.rs/vesti/politika/macut-zelena-transformacija-jedna-od-strateskih-politika-vlade/",
  "published": "Tue, 09 Dec 2025 16:54:24 +0000",
  "fetched_at": "2025-12-09T21:19:20.200390",
  "full_text": "<img alt=\"Macut: Zelena transformacija jedna od strateških politika Vlade 26\" class=\"attachment-medium size-medium wp-post-image\" height=\"169\" src=\"https://www.danas.rs/wp-content/uploads/2025/10/DJuro-Macut-RTS-printscreen-300x169.png\" style=\"float: left; margin: 0 10px 10px 0;\" title=\"Macut: Zelena transformacija jedna od strateških politika Vlade 49\" width=\"300\" />Predsednik Vlade Srbije Đuro Macut poručio je danas, na završnom događaju nacionalne ekološke kampanje za mlade \"Priroda nema alternativu. Zato deluj i ti!\", da je zelena transformacija jedna od strateških politika Vlade i da na tom putu nema važnijeg partnera od mladih."
}