{
  "id": "1154927cd66f0b9bfc50e5df801386746e08b99c0ca54d670236b548b4d2940e",
  "source": "Dnevni list Danas",
  "title": "Novi sistem merenja prekoračenja brzine – policija više ne mora da zaustavlja vozače",
  "subtitle": "<img alt=\"Novi sistem merenja prekoračenja brzine - policija više ne mora da zaustavlja vozače 23\" class=\"attachment-medium size-medium wp-post-image\" height=\"169\" src=\"https://www.danas.rs/wp-content/uploads/2025/09/Saobracajna-policija-Kragujevac-scaled-e1761902257280-300x169.jpg\" style=\"float: left; margin: 0 10px 10px 0;\" title=\"Novi sistem merenja prekoračenja brzine - policija više ne mora da zaustavlja vozače 31\" width=\"300\" />Saobraćajna policija u Srbiji počela je da primenjuje merenje brzine kretanja vozila bez potrebe zaustavljanja vozača.Policija koristi savremene radarske uređaje postavljene u službenim vozilima, ali i na posebno odabranim lokacijama bez prisustva vozila, saopštilo je Strukovno udruženje policije \"Dr Rudolf Arčibald Rajs\".",
  "url": "https://www.danas.rs/vesti/drustvo/novi-sistem-merenja-prekoracenja-brzine-policija-vise-ne-mora-da-zaustavlja-vozace/",
  "published": "Fri, 05 Dec 2025 12:33:15 +0000",
  "fetched_at": "2025-12-05T14:22:38.049730",
  "full_text": "<img alt=\"Novi sistem merenja prekoračenja brzine - policija više ne mora da zaustavlja vozače 23\" class=\"attachment-medium size-medium wp-post-image\" height=\"169\" src=\"https://www.danas.rs/wp-content/uploads/2025/09/Saobracajna-policija-Kragujevac-scaled-e1761902257280-300x169.jpg\" style=\"float: left; margin: 0 10px 10px 0;\" title=\"Novi sistem merenja prekoračenja brzine - policija više ne mora da zaustavlja vozače 31\" width=\"300\" />Saobraćajna policija u Srbiji počela je da primenjuje merenje brzine kretanja vozila bez potrebe zaustavljanja vozača.Policija koristi savremene radarske uređaje postavljene u službenim vozilima, ali i na posebno odabranim lokacijama bez prisustva vozila, saopštilo je Strukovno udruženje policije \"Dr Rudolf Arčibald Rajs\"."
}