{
  "id": "3060da5e33efff07c78d73bc3a255d194ed1baa7d07e151719c16ab705eee349",
  "source": "Dnevni list Danas",
  "title": "Šta kaže nauka – zašto volimo pse",
  "subtitle": "<img alt=\"Šta kaže nauka - zašto volimo pse 14\" class=\"attachment-medium size-medium wp-post-image\" height=\"169\" src=\"https://www.danas.rs/wp-content/uploads/2025/12/3463e1c0-d044-11f0-9fb5-5f3a3703a365-300x169.jpg\" style=\"float: left; margin: 0 10px 10px 0;\" title=\"Šta kaže nauka - zašto volimo pse 18\" width=\"300\" /><div>Psi su evoluirali od vukova, pa zašto su onda izabrali ljude za svoje najbolje prijatelje?</div>",
  "url": "https://www.danas.rs/bbc-news-serbian/sta-kaze-nauka-zasto-volimo-pse/",
  "published": "Sun, 21 Dec 2025 07:11:03 +0000",
  "fetched_at": "2025-12-21T09:21:36.973515",
  "full_text": "<img alt=\"Šta kaže nauka - zašto volimo pse 14\" class=\"attachment-medium size-medium wp-post-image\" height=\"169\" src=\"https://www.danas.rs/wp-content/uploads/2025/12/3463e1c0-d044-11f0-9fb5-5f3a3703a365-300x169.jpg\" style=\"float: left; margin: 0 10px 10px 0;\" title=\"Šta kaže nauka - zašto volimo pse 18\" width=\"300\" /><div>Psi su evoluirali od vukova, pa zašto su onda izabrali ljude za svoje najbolje prijatelje?</div>"
}