{
  "id": "34d61a8be41f2851c54f684913fec1ac0a0af9c590ac63118512f816c9569282",
  "source": "Dnevni list Danas",
  "title": "Navrocki i Zelenski: Imamo lošu vest za Moskvu",
  "subtitle": "<img alt=\"Navrocki i Zelenski: Imamo lošu vest za Moskvu 24\" class=\"attachment-medium size-medium wp-post-image\" height=\"170\" src=\"https://www.danas.rs/wp-content/uploads/2025/11/13543531-e1764500111736-300x170.jpg\" style=\"float: left; margin: 0 10px 10px 0;\" title=\"Navrocki i Zelenski: Imamo lošu vest za Moskvu 35\" width=\"300\" />Predsednik Poljske Karol Navrocki poručio je danas posle razgovora sa predsednikom Ukrajine Volodimirom Zelenskim u Varšavi da ima za Moskvu lošu vest: Poljska i Evropa su složne u strateškim pitanjima bezbednosti i pomoći Ukrajini ;i tu nema nikakvog osporavanja.",
  "url": "https://www.danas.rs/svet/navrocki-i-zelenski/",
  "published": "Fri, 19 Dec 2025 13:31:55 +0000",
  "fetched_at": "2025-12-19T17:20:02.650445",
  "full_text": "<img alt=\"Navrocki i Zelenski: Imamo lošu vest za Moskvu 24\" class=\"attachment-medium size-medium wp-post-image\" height=\"170\" src=\"https://www.danas.rs/wp-content/uploads/2025/11/13543531-e1764500111736-300x170.jpg\" style=\"float: left; margin: 0 10px 10px 0;\" title=\"Navrocki i Zelenski: Imamo lošu vest za Moskvu 35\" width=\"300\" />Predsednik Poljske Karol Navrocki poručio je danas posle razgovora sa predsednikom Ukrajine Volodimirom Zelenskim u Varšavi da ima za Moskvu lošu vest: Poljska i Evropa su složne u strateškim pitanjima bezbednosti i pomoći Ukrajini ;i tu nema nikakvog osporavanja."
}