{
  "id": "39818a28a5ebc6f58eb80b65da8389638454afac6729501575d33622e3e8d8c4",
  "source": "Dnevni list Danas",
  "title": "Egipat zainteresovan za uvoz srpske pšenice i kukuruza",
  "subtitle": "<img alt=\"Egipat zainteresovan za uvoz srpske pšenice i kukuruza 24\" class=\"attachment-medium size-medium wp-post-image\" height=\"169\" src=\"https://www.danas.rs/wp-content/uploads/2023/09/1405foto-EPA-EFE-KHALED-ELFIQI-e1766588822667-300x169.jpg\" style=\"float: left; margin: 0 10px 10px 0;\" title=\"Egipat zainteresovan za uvoz srpske pšenice i kukuruza 35\" width=\"300\" />Ambasador Egipta u Beogradu Ahmed Salam Soliman izjavio je danas na sastanku sa ministrom poljoprivrede Srbije Draganom Glamočićem da postoji veliko interesovanje egipatske strane za uvoz pšenice iz Srbije.",
  "url": "https://www.danas.rs/vesti/ekonomija/egipat-zainteresovan-za-uvoz-srpske-psenice-i-kukuruza/",
  "published": "Wed, 24 Dec 2025 15:07:08 +0000",
  "fetched_at": "2025-12-24T17:41:59.634121",
  "full_text": "<img alt=\"Egipat zainteresovan za uvoz srpske pšenice i kukuruza 24\" class=\"attachment-medium size-medium wp-post-image\" height=\"169\" src=\"https://www.danas.rs/wp-content/uploads/2023/09/1405foto-EPA-EFE-KHALED-ELFIQI-e1766588822667-300x169.jpg\" style=\"float: left; margin: 0 10px 10px 0;\" title=\"Egipat zainteresovan za uvoz srpske pšenice i kukuruza 35\" width=\"300\" />Ambasador Egipta u Beogradu Ahmed Salam Soliman izjavio je danas na sastanku sa ministrom poljoprivrede Srbije Draganom Glamočićem da postoji veliko interesovanje egipatske strane za uvoz pšenice iz Srbije."
}