{
  "id": "3bb2f152ddcb0d7a39bfaa051c8160b5280f693f489c554d0e453dbe026016e4",
  "source": "BBC News",
  "title": "New clashes break out between Pakistan and Taliban",
  "subtitle": "Both sides accuse the other of starting the overnight fighting and breaching a fragile ceasefire agreed in October.",
  "url": "https://www.bbc.com/news/articles/cn09zp87pz8o?at_medium=RSS&at_campaign=rss",
  "published": "Sat, 06 Dec 2025 04:58:43 GMT",
  "fetched_at": "2025-12-06T05:20:41.366347",
  "full_text": "Both sides accuse the other of starting the overnight fighting and breaching a fragile ceasefire agreed in October."
}