{
  "id": "42ea210c0f2ff1a546026befc31898b2b561aa3b23a88040f23ca5c0b45bf69d",
  "source": "Dnevni list Danas",
  "title": "Troje uhapšeno zbog sumnje da su izvršili prinudu i ugrozili sigurnost bračnog para",
  "subtitle": "<img alt=\"Troje uhapšeno zbog sumnje da su izvršili prinudu i ugrozili sigurnost bračnog para 18\" class=\"attachment-medium size-medium wp-post-image\" height=\"169\" src=\"https://www.danas.rs/wp-content/uploads/2022/11/Policijska-kola-Foto-N.-K.-1-e1669041130119-300x169.jpg\" style=\"float: left; margin: 0 10px 10px 0;\" title=\"Troje uhapšeno zbog sumnje da su izvršili prinudu i ugrozili sigurnost bračnog para 24\" width=\"300\" />Pripadnici Ministarstva unutrašnjih poslova (MUP) uhapsili su tri osobe zbog sumnje da su izvršili krivična dela prinuda i ugrožavanje sigurnosti, saopšteno je danas.\n\n&#160;\n\n&#160;",
  "url": "https://www.danas.rs/vesti/drustvo/troje-uhapseno-zbog-sumnje-da-su-izvrsili-prinudu-i-ugrozili-sigurnost-bracnog-para/",
  "published": "Mon, 15 Dec 2025 14:52:59 +0000",
  "fetched_at": "2025-12-15T16:33:54.408739",
  "full_text": "<img alt=\"Troje uhapšeno zbog sumnje da su izvršili prinudu i ugrozili sigurnost bračnog para 18\" class=\"attachment-medium size-medium wp-post-image\" height=\"169\" src=\"https://www.danas.rs/wp-content/uploads/2022/11/Policijska-kola-Foto-N.-K.-1-e1669041130119-300x169.jpg\" style=\"float: left; margin: 0 10px 10px 0;\" title=\"Troje uhapšeno zbog sumnje da su izvršili prinudu i ugrozili sigurnost bračnog para 24\" width=\"300\" />Pripadnici Ministarstva unutrašnjih poslova (MUP) uhapsili su tri osobe zbog sumnje da su izvršili krivična dela prinuda i ugrožavanje sigurnosti, saopšteno je danas.\n\n&#160;\n\n&#160;"
}