{
  "id": "43c7428c2c7b7f79c7dc1747a58c44ebd9c68953c418d1c49345dc64a9836d9c",
  "source": "Dnevni list Danas",
  "title": "Na Novom Beogradu umesto visokoškolske ustanove biće zgrade MUP-a",
  "subtitle": "<img alt=\"Na Novom Beogradu umesto visokoškolske ustanove biće zgrade MUP-a 35\" class=\"attachment-medium size-medium wp-post-image\" height=\"169\" src=\"https://www.danas.rs/wp-content/uploads/2024/07/shutterstock_2392920347-e1721939029575-300x169.jpg\" style=\"float: left; margin: 0 10px 10px 0;\" title=\"Na Novom Beogradu umesto visokoškolske ustanove biće zgrade MUP-a 45\" width=\"300\" />Ogroman kompleks Ministarstva unutrašnjih poslova biće izgrađen u sada uglavnom praznom Bloku 39 u Novom Beogradu, gde je Fakultet dramskih umetnosti (FDU), piše danas portal eKapija.",
  "url": "https://www.danas.rs/vesti/drustvo/na-novom-beogradu-umesto-visokoskolske-ustanove-bice-zgrade-mup-a/",
  "published": "Mon, 22 Dec 2025 13:58:05 +0000",
  "fetched_at": "2025-12-22T17:26:30.031376",
  "full_text": "<img alt=\"Na Novom Beogradu umesto visokoškolske ustanove biće zgrade MUP-a 35\" class=\"attachment-medium size-medium wp-post-image\" height=\"169\" src=\"https://www.danas.rs/wp-content/uploads/2024/07/shutterstock_2392920347-e1721939029575-300x169.jpg\" style=\"float: left; margin: 0 10px 10px 0;\" title=\"Na Novom Beogradu umesto visokoškolske ustanove biće zgrade MUP-a 45\" width=\"300\" />Ogroman kompleks Ministarstva unutrašnjih poslova biće izgrađen u sada uglavnom praznom Bloku 39 u Novom Beogradu, gde je Fakultet dramskih umetnosti (FDU), piše danas portal eKapija."
}