{
  "id": "452dd8531d1f3cf99761457b5161ba1421c6f6cb5a5b6069f951cdc3e5c409e3",
  "source": "Dnevni list Danas",
  "title": "Dodeljene nagrade Udruženja filmskih umetnika Srbije (UFUS) za 2025. godinu",
  "subtitle": "<img alt=\"Udruženje filmskih umetnika Srbije (UFUS) dodelilo nagrade za 2024: Mladen Đorđević i Miroslav Lekić među laueratima\" class=\"attachment-medium size-medium wp-post-image\" height=\"169\" src=\"https://www.danas.rs/wp-content/uploads/2024/12/reditelji_21122018_0023-e1733862842448-300x169.jpg\" style=\"float: left; margin: 0 10px 10px 0;\" title=\"Dodeljene nagrade Udruženja filmskih umetnika Srbije (UFUS) za 2025. godinu 41\" width=\"300\" />Udruženje filmskih umetnika Srbije (UFUS) dodelilo je danas nagrade za 2025. godinu za publicistiku, režiju i životno delo – scenaristkinji i rediteljki Aniti Panić, rediteljki Ivani Mladenović i scenografu Vladislavu Lašiću.",
  "url": "https://www.danas.rs/kultura/ufus-nagrade-2025/",
  "published": "Fri, 12 Dec 2025 16:55:40 +0000",
  "fetched_at": "2025-12-12T20:56:38.954612",
  "full_text": "<img alt=\"Udruženje filmskih umetnika Srbije (UFUS) dodelilo nagrade za 2024: Mladen Đorđević i Miroslav Lekić među laueratima\" class=\"attachment-medium size-medium wp-post-image\" height=\"169\" src=\"https://www.danas.rs/wp-content/uploads/2024/12/reditelji_21122018_0023-e1733862842448-300x169.jpg\" style=\"float: left; margin: 0 10px 10px 0;\" title=\"Dodeljene nagrade Udruženja filmskih umetnika Srbije (UFUS) za 2025. godinu 41\" width=\"300\" />Udruženje filmskih umetnika Srbije (UFUS) dodelilo je danas nagrade za 2025. godinu za publicistiku, režiju i životno delo – scenaristkinji i rediteljki Aniti Panić, rediteljki Ivani Mladenović i scenografu Vladislavu Lašiću."
}