{
  "id": "48eb45275cddc25bcf26d0d457ac222b234804d798779bb3985a7bf96127c853",
  "source": "Dnevni list Danas",
  "title": "Uhapšen bivši ministar poljoprivrede Crne Gore",
  "subtitle": "<img alt=\"crna gora policija\" class=\"attachment-medium size-medium wp-post-image\" height=\"169\" src=\"https://www.danas.rs/wp-content/uploads/2023/11/10934717-e1700307850565-300x169.jpg\" style=\"float: left; margin: 0 10px 10px 0;\" title=\"Uhapšen bivši ministar poljoprivrede Crne Gore 49\" width=\"300\" />Crnogorska policija uhapsila je jutros Milutina Simovića, ministra poljoprivrede iz perioda vladavine Demokratske partije socijalista (DPS), potvrdio je za Radio televiziju Crne Gore (RTCG) njegov pravni zastupnik.",
  "url": "https://www.danas.rs/svet/region/uhapsen-bivsi-ministar-poljoprivrede-crne-gore/",
  "published": "Mon, 22 Dec 2025 10:37:13 +0000",
  "fetched_at": "2025-12-22T14:25:15.948272",
  "full_text": "<img alt=\"crna gora policija\" class=\"attachment-medium size-medium wp-post-image\" height=\"169\" src=\"https://www.danas.rs/wp-content/uploads/2023/11/10934717-e1700307850565-300x169.jpg\" style=\"float: left; margin: 0 10px 10px 0;\" title=\"Uhapšen bivši ministar poljoprivrede Crne Gore 49\" width=\"300\" />Crnogorska policija uhapsila je jutros Milutina Simovića, ministra poljoprivrede iz perioda vladavine Demokratske partije socijalista (DPS), potvrdio je za Radio televiziju Crne Gore (RTCG) njegov pravni zastupnik."
}