{
  "id": "49bfc90f942516eb7d0d7b191183d5bce4ab95fd89a67767bc4bc9263a5ad9bb",
  "source": "Dnevni list Danas",
  "title": "Američki mediji: SAD ukinule sankcije Dodiku, ali upozorenje ostaje, Tramp neće dozvoliti manipulacije",
  "subtitle": "<img alt=\"Američki mediji: SAD ukinule sankcije Dodiku, ali upozorenje ostaje, Tramp neće dozvoliti manipulacije 37\" class=\"attachment-medium size-medium wp-post-image\" height=\"169\" src=\"https://www.danas.rs/wp-content/uploads/2025/11/13529910-e1764148243690-300x169.jpg\" style=\"float: left; margin: 0 10px 10px 0;\" title=\"Američki mediji: SAD ukinule sankcije Dodiku, ali upozorenje ostaje, Tramp neće dozvoliti manipulacije 49\" width=\"300\" />Ukidanjem sankcija, Sjedinjene Američke Države su verovatno imale za cilj smanjenje nestabilnosti i napetosti u regiji koja je još uvek žarište - a ne finansiranje \"lutkarske predstave\".",
  "url": "https://www.danas.rs/svet/region/washington-examiner-dodik-sankcije/",
  "published": "Sun, 21 Dec 2025 17:05:10 +0000",
  "fetched_at": "2025-12-22T06:37:46.907501",
  "full_text": "<img alt=\"Američki mediji: SAD ukinule sankcije Dodiku, ali upozorenje ostaje, Tramp neće dozvoliti manipulacije 37\" class=\"attachment-medium size-medium wp-post-image\" height=\"169\" src=\"https://www.danas.rs/wp-content/uploads/2025/11/13529910-e1764148243690-300x169.jpg\" style=\"float: left; margin: 0 10px 10px 0;\" title=\"Američki mediji: SAD ukinule sankcije Dodiku, ali upozorenje ostaje, Tramp neće dozvoliti manipulacije 49\" width=\"300\" />Ukidanjem sankcija, Sjedinjene Američke Države su verovatno imale za cilj smanjenje nestabilnosti i napetosti u regiji koja je još uvek žarište - a ne finansiranje \"lutkarske predstave\"."
}