{
  "id": "4d189e9e69f380a1d1584e1d2921c9b0dd91117cab90274e998dde1a8e2657c0",
  "source": "Dnevni list Danas",
  "title": "Vojska Mjanmara bombardovala bolnicu, među poginulima i deca",
  "subtitle": "<img alt=\"Vojska Mjanmara bombardovala bolnicu, među poginulima i deca 17\" class=\"attachment-medium size-medium wp-post-image\" height=\"174\" src=\"https://www.danas.rs/wp-content/uploads/2021/12/1701foto-EPA-EFE-300x174.jpg\" style=\"float: left; margin: 0 10px 10px 0;\" title=\"Vojska Mjanmara bombardovala bolnicu, među poginulima i deca 23\" width=\"300\" />Vojska Mjanmara potvrdila je danas da je u saveznoj državi Rakin na zapadu zemlje napala bolnicu, u kojoj je, kako vlasti tvrde, sedište militantne grupe, a poginulo je najmanje 30 osoba, uključujući pacijente i decu.",
  "url": "https://www.danas.rs/svet/vojska-mjanmara-bombardovala-bolnicu-medju-poginulima-i-deca/",
  "published": "Sat, 13 Dec 2025 09:46:25 +0000",
  "fetched_at": "2025-12-13T11:37:57.150008",
  "full_text": "<img alt=\"Vojska Mjanmara bombardovala bolnicu, među poginulima i deca 17\" class=\"attachment-medium size-medium wp-post-image\" height=\"174\" src=\"https://www.danas.rs/wp-content/uploads/2021/12/1701foto-EPA-EFE-300x174.jpg\" style=\"float: left; margin: 0 10px 10px 0;\" title=\"Vojska Mjanmara bombardovala bolnicu, među poginulima i deca 23\" width=\"300\" />Vojska Mjanmara potvrdila je danas da je u saveznoj državi Rakin na zapadu zemlje napala bolnicu, u kojoj je, kako vlasti tvrde, sedište militantne grupe, a poginulo je najmanje 30 osoba, uključujući pacijente i decu."
}