{
  "id": "5fbef58fab6b449fc779df8c68ed90c1ed3668e20bd5e45beecb9413649f1e2c",
  "source": "Dnevni list Danas",
  "title": "Vojska SAD gađala tri broda u istočnom Pacifiku: Ubijeno osam osoba",
  "subtitle": "<img alt=\"Vojska SAD gađala tri broda u istočnom Pacifiku: Ubijeno osam osoba 3\" class=\"attachment-medium size-medium wp-post-image\" height=\"169\" src=\"https://www.danas.rs/wp-content/uploads/2025/12/13255082-e1764941394413-300x169.jpg\" style=\"float: left; margin: 0 10px 10px 0;\" title=\"Vojska SAD gađala tri broda u istočnom Pacifiku: Ubijeno osam osoba 5\" width=\"300\" />Američka vojska saopštila je sinoć da je napala tri broda navodeći da krijumčare drogu u istočnom Pacifiku, ubijeno je osam osoba, a u isto vreme ispitivanje oko udara na brodove pojačava se u Kongresu.",
  "url": "https://www.danas.rs/svet/vojska-sad-ubistvo-brodovi/",
  "published": "Tue, 16 Dec 2025 07:33:50 +0000",
  "fetched_at": "2025-12-16T07:52:40.484253",
  "full_text": "<img alt=\"Vojska SAD gađala tri broda u istočnom Pacifiku: Ubijeno osam osoba 3\" class=\"attachment-medium size-medium wp-post-image\" height=\"169\" src=\"https://www.danas.rs/wp-content/uploads/2025/12/13255082-e1764941394413-300x169.jpg\" style=\"float: left; margin: 0 10px 10px 0;\" title=\"Vojska SAD gađala tri broda u istočnom Pacifiku: Ubijeno osam osoba 5\" width=\"300\" />Američka vojska saopštila je sinoć da je napala tri broda navodeći da krijumčare drogu u istočnom Pacifiku, ubijeno je osam osoba, a u isto vreme ispitivanje oko udara na brodove pojačava se u Kongresu."
}