{
  "id": "636ffe41e09fc89ace2ac07dc2aeeb9ce812be999f757299d6b9be637fe0fa1c",
  "source": "BBC News",
  "title": "What we know so far about the Brown University shooting",
  "subtitle": "The identities of those killed or injured have not yet been released, but the university said all the victims were students.",
  "url": "https://www.bbc.com/news/articles/ckg9l1j9wxno?at_medium=RSS&at_campaign=rss",
  "published": "Sun, 14 Dec 2025 14:57:08 GMT",
  "fetched_at": "2025-12-14T17:40:43.030168",
  "full_text": "The identities of those killed or injured have not yet been released, but the university said all the victims were students."
}