{
  "id": "6c9c7176f41bc20d50c3d2d3dd6311311ee67ff30032f1910ec895ad91bcb63c",
  "source": "BBC News",
  "title": "Deadly border fighting breaks out between Pakistan and Taliban",
  "subtitle": "Both sides accuse the other of starting the overnight fighting and breaching a fragile ceasefire agreed in October.",
  "url": "https://www.bbc.com/news/articles/cn09zp87pz8o?at_medium=RSS&at_campaign=rss",
  "published": "Sat, 06 Dec 2025 04:58:43 GMT",
  "fetched_at": "2025-12-06T05:52:58.740897",
  "full_text": "Both sides accuse the other of starting the overnight fighting and breaching a fragile ceasefire agreed in October."
}