{
  "id": "6d7948f0365a98d79a4660291823997a99111d4de1e01c3aff61f67306257a4a",
  "source": "Dnevni list Danas",
  "title": "Snimak Stare planine osvojio prvo mesto na konkursu „Viki voli Zemlju 2025“ (VIDEO)",
  "subtitle": "<img alt=\"Snimak Stare planine osvojio prvo mesto na konkursu &quot;Viki voli Zemlju 2025&quot; (VIDEO) 38\" class=\"attachment-medium size-medium wp-post-image\" height=\"169\" src=\"https://www.danas.rs/wp-content/uploads/2025/12/Stara-Planina-snimak--300x169.jpg\" style=\"float: left; margin: 0 10px 10px 0;\" title=\"Snimak Stare planine osvojio prvo mesto na konkursu &quot;Viki voli Zemlju 2025&quot; (VIDEO) 45\" width=\"300\" />Video-snimak Stare planine iz vazduha, autora Marka Dekića osvojio je prvo mesto na međunarodnom nivou konkursa Viki voli Zemlju 2025, saopštili su danas organizatori.",
  "url": "https://www.danas.rs/vesti/klimatske-promene/stara-planina-snimak/",
  "published": "Fri, 19 Dec 2025 08:49:15 +0000",
  "fetched_at": "2025-12-19T11:40:20.037736",
  "full_text": "<img alt=\"Snimak Stare planine osvojio prvo mesto na konkursu &quot;Viki voli Zemlju 2025&quot; (VIDEO) 38\" class=\"attachment-medium size-medium wp-post-image\" height=\"169\" src=\"https://www.danas.rs/wp-content/uploads/2025/12/Stara-Planina-snimak--300x169.jpg\" style=\"float: left; margin: 0 10px 10px 0;\" title=\"Snimak Stare planine osvojio prvo mesto na konkursu &quot;Viki voli Zemlju 2025&quot; (VIDEO) 45\" width=\"300\" />Video-snimak Stare planine iz vazduha, autora Marka Dekića osvojio je prvo mesto na međunarodnom nivou konkursa Viki voli Zemlju 2025, saopštili su danas organizatori."
}