{
  "id": "75e43fffdf57683ed0cbdb94ff502abefa2e44d119176fafa8abebb8f6bd51cc",
  "source": "Dnevni list Danas",
  "title": "PSG usvojio deklaraciju: „Evropa, izbor slobodnih građana“",
  "subtitle": "<img alt=\"Pavle Grbović (PSG)\" class=\"attachment-medium size-medium wp-post-image\" height=\"169\" src=\"https://www.danas.rs/wp-content/uploads/2025/04/0402foto-FoNet-Milica-Vuckovic-e1746991042699-300x169.jpg\" style=\"float: left; margin: 0 10px 10px 0;\" title=\"PSG usvojio deklaraciju: &quot;Evropa, izbor slobodnih građana&quot; 16\" width=\"300\" />Pokret slobodnih građana (PSG) saopštio je da je danas na sednici Glavnog odbora usvojio deklaraciju \"Evropa, izbor slobodnih građana\", kojom taj pokret jasno pokazuje da je prepoznao svoju ulogu i profilisao se kao jedan od lidera proevropske Srbije.",
  "url": "https://www.danas.rs/vesti/politika/psg-usvojio-deklaraciju-evropa-izbor-slobodnih-gradjana/",
  "published": "Sun, 21 Dec 2025 12:31:03 +0000",
  "fetched_at": "2025-12-21T14:41:42.046292",
  "full_text": "<img alt=\"Pavle Grbović (PSG)\" class=\"attachment-medium size-medium wp-post-image\" height=\"169\" src=\"https://www.danas.rs/wp-content/uploads/2025/04/0402foto-FoNet-Milica-Vuckovic-e1746991042699-300x169.jpg\" style=\"float: left; margin: 0 10px 10px 0;\" title=\"PSG usvojio deklaraciju: &quot;Evropa, izbor slobodnih građana&quot; 16\" width=\"300\" />Pokret slobodnih građana (PSG) saopštio je da je danas na sednici Glavnog odbora usvojio deklaraciju \"Evropa, izbor slobodnih građana\", kojom taj pokret jasno pokazuje da je prepoznao svoju ulogu i profilisao se kao jedan od lidera proevropske Srbije."
}