{
  "id": "856ee83535230093c31093af8e03223e315ced6bf3ae13e245f3492749da325f",
  "source": "BBC News",
  "title": "Details of plan to keep pubs open longer for World Cup revealed",
  "subtitle": "Licensing hours could be extended to 01:00 if a home nation reaches the final stages next summer.",
  "url": "https://www.bbc.com/news/articles/czrkymn8l2yo?at_medium=RSS&at_campaign=rss",
  "published": "Fri, 05 Dec 2025 02:09:09 GMT",
  "fetched_at": "2025-12-05T03:20:17.961753",
  "full_text": "Licensing hours could be extended to 01:00 if a home nation reaches the final stages next summer."
}