{
  "id": "943c1ca08e30ce3133d9b151d55186300e5779cd763ca227b2be51b36dbe5b31",
  "source": "Dnevni list Danas",
  "title": "Jovanović: Desnica će doprineti pobedi",
  "subtitle": "<img alt=\"Jovanović: Desnica će doprineti pobedi 19\" class=\"attachment-medium size-medium wp-post-image\" height=\"195\" src=\"https://www.danas.rs/wp-content/uploads/2025/09/4-30-300x195.jpg\" style=\"float: left; margin: 0 10px 10px 0;\" title=\"Jovanović: Desnica će doprineti pobedi 37\" width=\"300\" />Predsednik Nove Demokaratske stranke Srbije Miloš Jovanović izjavio je danas da će „rezultat autentične desnice na predstojećim parlamentarnim izborima biti odličan“ i da će „doprineti smeni izdajničkog režima“.",
  "url": "https://www.danas.rs/vesti/politika/jovanovic-desnica-ce-doprineti-pobedi/",
  "published": "Tue, 23 Dec 2025 18:47:29 +0000",
  "fetched_at": "2025-12-23T23:20:39.492625",
  "full_text": "<img alt=\"Jovanović: Desnica će doprineti pobedi 19\" class=\"attachment-medium size-medium wp-post-image\" height=\"195\" src=\"https://www.danas.rs/wp-content/uploads/2025/09/4-30-300x195.jpg\" style=\"float: left; margin: 0 10px 10px 0;\" title=\"Jovanović: Desnica će doprineti pobedi 37\" width=\"300\" />Predsednik Nove Demokaratske stranke Srbije Miloš Jovanović izjavio je danas da će „rezultat autentične desnice na predstojećim parlamentarnim izborima biti odličan“ i da će „doprineti smeni izdajničkog režima“."
}