{
  "id": "98e0f276c27c6a4650cbaf2db5677ce39a8a6d9d20021a6b73967cf5b8a9c673",
  "source": "Dnevni list Danas",
  "title": "Putevi Srbije: Putni pravci prohodni, moguća poledica i magla",
  "subtitle": "<img alt=\"Putevi Srbije: Putni pravci prohodni, moguća poledica i magla 1\" class=\"attachment-medium size-medium wp-post-image\" height=\"169\" src=\"https://www.danas.rs/wp-content/uploads/2025/11/magla-hladno-vreme-e1765125094836-300x169.jpg\" style=\"float: left; margin: 0 10px 10px 0;\" title=\"Putevi Srbije: Putni pravci prohodni, moguća poledica i magla 2\" width=\"300\" />- Najopterećeniji putni pravci su prohodni i nema snega saopštilo je danas Javno preduzeće \"Putevi Srbije\".",
  "url": "https://www.danas.rs/vesti/drustvo/putevi-srbije-putni-pravci-prohodni-moguca-poledica-i-magla/",
  "published": "Sun, 07 Dec 2025 16:33:01 +0000",
  "fetched_at": "2025-12-07T16:44:38.107063",
  "full_text": "<img alt=\"Putevi Srbije: Putni pravci prohodni, moguća poledica i magla 1\" class=\"attachment-medium size-medium wp-post-image\" height=\"169\" src=\"https://www.danas.rs/wp-content/uploads/2025/11/magla-hladno-vreme-e1765125094836-300x169.jpg\" style=\"float: left; margin: 0 10px 10px 0;\" title=\"Putevi Srbije: Putni pravci prohodni, moguća poledica i magla 2\" width=\"300\" />- Najopterećeniji putni pravci su prohodni i nema snega saopštilo je danas Javno preduzeće \"Putevi Srbije\"."
}