{
  "id": "9af1ef21a2a9a26c4faf19ef2fb68cbaafdff3ccadf08a68412589b10162811d",
  "source": "BBC News",
  "title": "When Billie Jean beat Bobby - the Battle of the Sexes that defined an era",
  "subtitle": "When Aryna Sabalenka faces Nick Kyrgios, it will be under the banner of the Battle of the Sexes - but the stakes will not be as high as those that faced Billie Jean King 52 years ago.",
  "url": "https://www.bbc.com/sport/tennis/articles/cy95g0q9qrzo?at_medium=RSS&at_campaign=rss",
  "published": "Sat, 27 Dec 2025 06:17:47 GMT",
  "fetched_at": "2025-12-27T06:33:35.520274",
  "full_text": "When Aryna Sabalenka faces Nick Kyrgios, it will be under the banner of the Battle of the Sexes - but the stakes will not be as high as those that faced Billie Jean King 52 years ago."
}