{
  "id": "9c4ee7e0c37efd6fa44c901778120903cf369563ccf467d4e175e33994dd8e67",
  "source": "Dnevni list Danas",
  "title": "Maradonin dres prodat po rekordnoj cifri",
  "subtitle": "<img alt=\"Dijego Armando Maradona\" class=\"attachment-medium size-medium wp-post-image\" height=\"169\" src=\"https://www.danas.rs/wp-content/uploads/2025/12/13129647-e1766692645106-300x169.jpg\" style=\"float: left; margin: 0 10px 10px 0;\" title=\"Maradonin dres prodat po rekordnoj cifri 6\" width=\"300\" />Legendarni fudbaler Dijego Armando Maradona preminuo je u novembru 2020. godine u 60. godini.",
  "url": "https://www.danas.rs/sport/dijego-armando-maradona-pordat-dres-aukcija/",
  "published": "Thu, 25 Dec 2025 20:02:55 +0000",
  "fetched_at": "2025-12-25T20:44:34.257939",
  "full_text": "<img alt=\"Dijego Armando Maradona\" class=\"attachment-medium size-medium wp-post-image\" height=\"169\" src=\"https://www.danas.rs/wp-content/uploads/2025/12/13129647-e1766692645106-300x169.jpg\" style=\"float: left; margin: 0 10px 10px 0;\" title=\"Maradonin dres prodat po rekordnoj cifri 6\" width=\"300\" />Legendarni fudbaler Dijego Armando Maradona preminuo je u novembru 2020. godine u 60. godini."
}