{
  "id": "9cfb6743bfda3c9cd612630d417951b37f51c833e9ecb72f0c4e9c55fe53dfe9",
  "source": "BBC News",
  "title": "US lawmakers threaten legal action against Attorney General over Epstein files",
  "subtitle": "A Republican and a Democrat who have led calls for transparency say the justice department failed to meet legal obligations.",
  "url": "https://www.bbc.com/news/articles/cdd5j9jdvy9o?at_medium=RSS&at_campaign=rss",
  "published": "Mon, 22 Dec 2025 11:27:54 GMT",
  "fetched_at": "2025-12-22T16:33:18.867031",
  "full_text": "A Republican and a Democrat who have led calls for transparency say the justice department failed to meet legal obligations."
}