{
  "id": "a977c0c4a1e9d6866e97d5b403d5522dc7f459c95d12e1582e50c2747034d0af",
  "source": "Dnevni list Danas",
  "title": "Sedam neobičnih božićnih običaja",
  "subtitle": "<img alt=\"Sedam neobičnih božićnih običaja 28\" class=\"attachment-medium size-medium wp-post-image\" height=\"169\" src=\"https://www.danas.rs/wp-content/uploads/2025/12/ad16ea80-d685-11f0-b4a3-21322b24f057-300x169.jpg\" style=\"float: left; margin: 0 10px 10px 0;\" title=\"Sedam neobičnih božićnih običaja 35\" width=\"300\" /><div>Ovih sedam tradicija u različitim krajevima sveta otkrivaju drugačiju stranu praznične sezone - onu koja podstiče zajedništvo i promišljanje i koja je mnogo manje materijalistička.</div>",
  "url": "https://www.danas.rs/bbc-news-serbian/sedam-neobicnih-bozicnih-obicaja/",
  "published": "Wed, 24 Dec 2025 06:20:16 +0000",
  "fetched_at": "2025-12-24T08:59:42.153201",
  "full_text": "<img alt=\"Sedam neobičnih božićnih običaja 28\" class=\"attachment-medium size-medium wp-post-image\" height=\"169\" src=\"https://www.danas.rs/wp-content/uploads/2025/12/ad16ea80-d685-11f0-b4a3-21322b24f057-300x169.jpg\" style=\"float: left; margin: 0 10px 10px 0;\" title=\"Sedam neobičnih božićnih običaja 35\" width=\"300\" /><div>Ovih sedam tradicija u različitim krajevima sveta otkrivaju drugačiju stranu praznične sezone - onu koja podstiče zajedništvo i promišljanje i koja je mnogo manje materijalistička.</div>"
}