{
  "id": "ac583999b770e859232eee661639493691ef182967b7dbd276925112353ff86a",
  "source": "BBC News",
  "title": "Airbnb fined £56m by Spain for advertising unlicensed properties",
  "subtitle": "The government has been cracking down on the rentals firm as neighbourhoods protest against holiday lets.",
  "url": "https://www.bbc.com/news/articles/cgke2x6vz66o?at_medium=RSS&at_campaign=rss",
  "published": "Mon, 15 Dec 2025 12:14:46 GMT",
  "fetched_at": "2025-12-15T12:50:57.238709",
  "full_text": "The government has been cracking down on the rentals firm as neighbourhoods protest against holiday lets."
}