{
  "id": "ad6d543d2656232d601b02054721652ca5331d34d41fa68a943feed4eb82a3cd",
  "source": "Dnevni list Danas",
  "title": "Zasedao Beogradski SNS, posetio ih Vučević",
  "subtitle": "<img alt=\"Zasedao Beogradski SNS, posetio ih Vučević 24\" class=\"attachment-medium size-medium wp-post-image\" height=\"169\" src=\"https://www.danas.rs/wp-content/uploads/2025/12/snsbeograd-e1766750382234-300x169.jpg\" style=\"float: left; margin: 0 10px 10px 0;\" title=\"Zasedao Beogradski SNS, posetio ih Vučević 27\" width=\"300\" />Miloš Vučević, predsednik Srpske napredne stranke, objavio je da je zasedao Beogradski odbor SNS, i da je on prisustvovao sednici. Sednicu su još vodili Ana Brnabić, predsednica Narodne skupštine, i Aleksandar Šapić, gradonačelnik Beograda.",
  "url": "https://www.danas.rs/vesti/politika/zasedao-beogradski-sns-posetio-ih-vucevic/",
  "published": "Fri, 26 Dec 2025 12:02:58 +0000",
  "fetched_at": "2025-12-26T13:49:52.870013",
  "full_text": "<img alt=\"Zasedao Beogradski SNS, posetio ih Vučević 24\" class=\"attachment-medium size-medium wp-post-image\" height=\"169\" src=\"https://www.danas.rs/wp-content/uploads/2025/12/snsbeograd-e1766750382234-300x169.jpg\" style=\"float: left; margin: 0 10px 10px 0;\" title=\"Zasedao Beogradski SNS, posetio ih Vučević 27\" width=\"300\" />Miloš Vučević, predsednik Srpske napredne stranke, objavio je da je zasedao Beogradski odbor SNS, i da je on prisustvovao sednici. Sednicu su još vodili Ana Brnabić, predsednica Narodne skupštine, i Aleksandar Šapić, gradonačelnik Beograda."
}