{
  "id": "c017ab43c763b395acf5f738be70b6fc06e66fa435c7fb7c17dbc47776de2af0",
  "source": "BBC News",
  "title": "Attack on Kyiv shows 'Russia doesn't want peace', Zelensky says",
  "subtitle": "The 10-hour missile and drone barrage directed at Ukraine's capital killed two people and left 32 injured, local authorities said.",
  "url": "https://www.bbc.com/news/articles/c1dzvpg1341o?at_medium=RSS&at_campaign=rss",
  "published": "Sat, 27 Dec 2025 19:19:02 GMT",
  "fetched_at": "2025-12-27T19:38:16.581949",
  "full_text": "The 10-hour missile and drone barrage directed at Ukraine's capital killed two people and left 32 injured, local authorities said."
}