{
  "id": "c329f7680a188cd051f6dd25ebc792afc9f970af3ce60ebe1ce3f4aabe8769d0",
  "source": "BBC News",
  "title": "Briton who fought in Ukraine jailed for 13 years by Russia",
  "subtitle": "Former British soldier Hayden Davies, labelled a mercenary by Russia, will be sent to a maximum-security prison.",
  "url": "https://www.bbc.com/news/articles/c30jre652gvo?at_medium=RSS&at_campaign=rss",
  "published": "Thu, 18 Dec 2025 11:33:12 GMT",
  "fetched_at": "2025-12-18T11:41:17.542844",
  "full_text": "Former British soldier Hayden Davies, labelled a mercenary by Russia, will be sent to a maximum-security prison."
}