{
  "id": "cf0942357240b762c5b4c820f6de6874609f4ad1d7d9adb65916e8f1cfc04cb0",
  "source": "BBC News",
  "title": "Watch: Cameras on killer whales record first evidence of joint hunt with dolphins",
  "subtitle": "Researchers say the footage, captured near the North-West Pacific coast, is the first recorded evidence of the two working together.",
  "url": "https://www.bbc.com/news/videos/ceq1000742go?at_medium=RSS&at_campaign=rss",
  "published": "Thu, 11 Dec 2025 18:03:29 GMT",
  "fetched_at": "2025-12-11T18:59:57.971712",
  "full_text": "Researchers say the footage, captured near the North-West Pacific coast, is the first recorded evidence of the two working together."
}