{
  "id": "cf1af0e8710612e06937e7c3ff56d3ad87d3f53b50a77dda9b5fe2039f4bd236",
  "source": "BBC News",
  "title": "How WhatsApp messages revealed ex-Reform politician's pro-Russian bribes",
  "subtitle": "The former leader of Reform UK in Wales has admitted bribery and will be sentenced on Friday.",
  "url": "https://www.bbc.com/news/articles/cn8vnv3dk0vo?at_medium=RSS&at_campaign=rss",
  "published": "Fri, 21 Nov 2025 16:04:21 GMT",
  "fetched_at": "2025-12-03T23:17:01.638260",
  "full_text": "The former leader of Reform UK in Wales has admitted bribery and will be sentenced on Friday."
}