{
  "id": "d24b4e44eaab42e1a1624e4a8bff1c7c876693d60d7e4393baa1e35046013adc",
  "source": "BBC News",
  "title": "'Living off grid is not a dream, it's a nightmare'",
  "subtitle": "Off-grid households say they would love a mains connection, but the price is just too high.",
  "url": "https://www.bbc.com/news/articles/cvgd9l8wxjpo?at_medium=RSS&at_campaign=rss",
  "published": "Tue, 09 Dec 2025 00:11:47 GMT",
  "fetched_at": "2025-12-09T01:45:42.899229",
  "full_text": "Off-grid households say they would love a mains connection, but the price is just too high."
}