{
  "id": "db32fbb158b9a92c5fa6269d8446c2693114536c3158b4f050cd6136e8a93bb6",
  "source": "Dnevni list Danas",
  "title": "Prvi potez srpskih gradonačelnika na severu Kosova",
  "subtitle": "<img alt=\"Prvi potez srpskih gradonačelnika na severu Kosova 20\" class=\"attachment-medium size-medium wp-post-image\" height=\"169\" src=\"https://www.danas.rs/wp-content/uploads/2025/12/lazic-sinisa-osmani-e1764935010221-300x169.jpg\" style=\"float: left; margin: 0 10px 10px 0;\" title=\"Prvi potez srpskih gradonačelnika na severu Kosova 47\" width=\"300\" />Novoizabrani gradonačelnici četiri opštine na severu Kosova, koji su u petak stupili na dužnost, razrešili su danas sve politički imenovane direktore opštinskih odeljenja.",
  "url": "https://www.danas.rs/vesti/politika/prvi-potez-srpskih-gradonacelnika-na-severu-kosova/",
  "published": "Mon, 08 Dec 2025 17:06:17 +0000",
  "fetched_at": "2025-12-08T22:21:09.816779",
  "full_text": "<img alt=\"Prvi potez srpskih gradonačelnika na severu Kosova 20\" class=\"attachment-medium size-medium wp-post-image\" height=\"169\" src=\"https://www.danas.rs/wp-content/uploads/2025/12/lazic-sinisa-osmani-e1764935010221-300x169.jpg\" style=\"float: left; margin: 0 10px 10px 0;\" title=\"Prvi potez srpskih gradonačelnika na severu Kosova 47\" width=\"300\" />Novoizabrani gradonačelnici četiri opštine na severu Kosova, koji su u petak stupili na dužnost, razrešili su danas sve politički imenovane direktore opštinskih odeljenja."
}