{
  "id": "ec43742dac5619725861aef50106966c15c1e0bda1882c2642430058e73f5bcc",
  "source": "BBC News",
  "title": "Australia's beloved weather website got a makeover - and infuriated users",
  "subtitle": "Nicknamed the Bom, the country's weather agency has been heavily criticised over a recent redesign.",
  "url": "https://www.bbc.com/news/articles/c2k4dy15nqqo?at_medium=RSS&at_campaign=rss",
  "published": "Wed, 26 Nov 2025 19:18:58 GMT",
  "fetched_at": "2025-12-03T23:17:00.801655",
  "full_text": "Nicknamed the Bom, the country's weather agency has been heavily criticised over a recent redesign."
}