{
  "id": "f3841dc4519ccb8db72a33e5f1b442f05945ce1d606b659fa547a7d63984fb6c",
  "source": "Dnevni list Danas",
  "title": "Može li Evrovizija da prevaziđe najveću krizu u istoriji",
  "subtitle": "<img alt=\"Može li Evrovizija da prevaziđe najveću krizu u istoriji 27\" class=\"attachment-medium size-medium wp-post-image\" height=\"169\" src=\"https://www.danas.rs/wp-content/uploads/2025/12/edef84c0-d1d2-11f0-9c0d-83f64f80aa08-300x169.jpg\" style=\"float: left; margin: 0 10px 10px 0;\" title=\"Može li Evrovizija da prevaziđe najveću krizu u istoriji 42\" width=\"300\" /><div>Odluka nekolicine zemalja da bojkotuje takmičenje 2026 (a spisak možda nije konačan), iznosi na videlo duboki jaz unutar evrovizijske porodice.</div>",
  "url": "https://www.danas.rs/bbc-news-serbian/moze-li-evrovizija-da-prevazidje-najvecu-krizu-u-istoriji/",
  "published": "Fri, 05 Dec 2025 14:30:04 +0000",
  "fetched_at": "2025-12-05T17:25:26.621262",
  "full_text": "<img alt=\"Može li Evrovizija da prevaziđe najveću krizu u istoriji 27\" class=\"attachment-medium size-medium wp-post-image\" height=\"169\" src=\"https://www.danas.rs/wp-content/uploads/2025/12/edef84c0-d1d2-11f0-9c0d-83f64f80aa08-300x169.jpg\" style=\"float: left; margin: 0 10px 10px 0;\" title=\"Može li Evrovizija da prevaziđe najveću krizu u istoriji 42\" width=\"300\" /><div>Odluka nekolicine zemalja da bojkotuje takmičenje 2026 (a spisak možda nije konačan), iznosi na videlo duboki jaz unutar evrovizijske porodice.</div>"
}