{
  "id": "fa381f781005a434dc25d95a4ce5f6d87fff0e443f0e7d48ec131ed797f0bcb4",
  "source": "BBC News",
  "title": "Thai PM dissolves parliament to 'return power to people'",
  "subtitle": "The dissolution order comes after Anutin Charnvirakul lost the support of the largest opposition bloc.",
  "url": "https://www.bbc.com/news/articles/c3v11rd200yo?at_medium=RSS&at_campaign=rss",
  "published": "Fri, 12 Dec 2025 02:06:39 GMT",
  "fetched_at": "2025-12-12T11:21:30.560679",
  "full_text": "The dissolution order comes after Anutin Charnvirakul lost the support of the largest opposition bloc."
}