{
  "id": "ff460831a6d115d53ddbe862a93242fc3de5068656973029e08bee89138c78ac",
  "source": "Dnevni list Danas",
  "title": "„U narednih nekoliko dana očekujemo važne vesti“: Vučić o sankcijama NIS-u",
  "subtitle": "<img alt=\"Aleksandar Vučić\" class=\"attachment-medium size-medium wp-post-image\" height=\"169\" src=\"https://www.danas.rs/wp-content/uploads/2025/12/1-17-e1764667187776-300x169.jpg\" style=\"float: left; margin: 0 10px 10px 0;\" title=\"&quot;U narednih nekoliko dana očekujemo važne vesti&quot;: Vučić o sankcijama NIS-u 41\" width=\"300\" />Aleksandar Vučić, predsednik Srbije u obraćanju javnosti u Palati Srbije, govoreći o sankcijama NIS-u, poručio je da očekuje \"važne vesti\".",
  "url": "https://www.danas.rs/vesti/ekonomija/u-narednih-nekoliko-dana-ocekujemo-vazne-vesti-vucic-o-sankcijama-nis-u/",
  "published": "Tue, 16 Dec 2025 11:16:05 +0000",
  "fetched_at": "2025-12-16T13:39:39.486508",
  "full_text": "<img alt=\"Aleksandar Vučić\" class=\"attachment-medium size-medium wp-post-image\" height=\"169\" src=\"https://www.danas.rs/wp-content/uploads/2025/12/1-17-e1764667187776-300x169.jpg\" style=\"float: left; margin: 0 10px 10px 0;\" title=\"&quot;U narednih nekoliko dana očekujemo važne vesti&quot;: Vučić o sankcijama NIS-u 41\" width=\"300\" />Aleksandar Vučić, predsednik Srbije u obraćanju javnosti u Palati Srbije, govoreći o sankcijama NIS-u, poručio je da očekuje \"važne vesti\"."
}